[{"Year":2001,"State":"CT","name":"Aedes c. canadensis","total":1},{"Year":2001,"State":"CT","name":"Aedes cinereus","total":1},{"Year":2001,"State":"CT","name":"Aedes sollicitans","total":1},{"Year":2001,"State":"CT","name":"Aedes taeniorhynchus","total":1},{"Year":2001,"State":"CT","name":"Anopheles punctipennis","total":1},{"Year":2001,"State":"CT","name":"Culex pipiens","total":13},{"Year":2001,"State":"CT","name":"Culex restuans","total":1},{"Year":2001,"State":"CT","name":"Culex salinarius","total":6},{"Year":2001,"State":"CT","name":"Culiseta melanura","total":5},{"Year":2001,"State":"CT","name":"Uranotaenia sapphirina","total":1},{"Year":2001,"State":"MA","name":"Aedes j. japonicus","total":1},{"Year":2001,"State":"MA","name":"Culex pipiens","total":7},{"Year":2001,"State":"MA","name":"Culex restuans","total":5},{"Year":2001,"State":"MA","name":"Culex sp.","total":9},{"Year":2001,"State":"MA","name":"Culiseta melanura","total":3},{"Year":2001,"State":"NH","name":"Aedes triseriatus","total":1},{"Year":2001,"State":"NH","name":"Culex pipiens-restuans (Mixed)","total":2},{"Year":2001,"State":"RI","name":"Aedes c. canadensis","total":2},{"Year":2001,"State":"RI","name":"Aedes cantator","total":1},{"Year":2001,"State":"RI","name":"Aedes vexans","total":1},{"Year":2001,"State":"RI","name":"Anopheles punctipennis","total":1},{"Year":2001,"State":"RI","name":"Anopheles quadrimaculatus s.l.","total":2},{"Year":2001,"State":"RI","name":"Coquillettidia perturbans","total":2},{"Year":2001,"State":"RI","name":"Culex sp.","total":3},{"Year":2001,"State":"RI","name":"Culiseta sp.","total":1},{"Year":2001,"State":"RI","name":"Orthopodomyia signifera","total":1}]